Workbook

Sheet Raw Data
A1: Order ID | B1: Order Date | C1: Product | D1: Category | E1: Quantity | F1: Unit Price | G1: Sales Amount | H1: Payment Method | I1: Customer Type | J1: City | K1: Sales Channel
A2: EC2001 | B2: 46118 | C2: Phone Charger | D2: Electronics | E2: 3 | F2: 7500 | G2: 22500 | H2: Card | I2: New | J2: Benin City | K2: Marketplace
A3: EC2002 | B3: 46150 | C3: Hoodie | D3: Fashion | E3: 4 | F3: 17500 | G3: 70000 | H3: Cash | I3: New | J3: Lagos | K3: Website
A4: EC2003 | B4: 46158 | C4: Phone Charger | D4: Electronics | E4: 3 | F4: 7500 | G4: 22500 | H4: Card | I4: Returning | J4: Lagos | K4: Marketplace
A5: EC2004 | B5: 46080 | C5: Sneakers | D5: Fashion | E5: 3 | F5: 28000 | G5: 84000 | H5: Cash | I5: Returning | J5: Abuja | K5: WhatsApp
A6: EC2005 | B6: 46149 | C6: Hoodie | D6: Fashion | E6: 4 | F6: 17500 | G6: 70000 | H6: Card | I6: Returning | J6: Lagos | K6: WhatsApp
A7: EC2006 | B7: 46072 | C7: Backpack | D7: Accessories | E7: 4 | F7: 18000 | G7: 72000 | H7: POS | I7: New | J7: Abuja | K7: WhatsApp
A8: EC2007 | B8: 46065 | C8: Notebook | D8: Stationery | E8: 4 | F8: 2500 | G8: 10000 | H8: Cash | I8: Returning | J8: Lagos | K8: Marketplace
A9: EC2008 | B9: 46104 | C9: Gel Pen Pack | D9: Stationery | E9: 4 | F9: 1800 | G9: 7200 | H9: POS | I9: Returning | J9: Benin City | K9: Marketplace
A10: EC2009 | B10: 46127 | C10: Gel Pen Pack | D10: Stationery | E10: 1 | F10: 1800 | G10: 1800 | H10: Transfer | I10: New | J10: Lagos | K10: Website
A11: EC2010 | B11: 46114 | C11: T-Shirt | D11: Fashion | E11: 4 | F11: 9500 | G11: 38000 | H11: Transfer | I11: Returning | J11: Ibadan | K11: Website
A12: EC2011 | B12: 46140 | C12: Sneakers | D12: Fashion | E12: 4 | F12: 28000 | G12: 112000 | H12: Cash | I12: Returning | J12: Benin City | K12: Marketplace
A13: EC2012 | B13: 46124 | C13: Sneakers | D13: Fashion | E13: 3 | F13: 28000 | G13: 84000 | H13: Cash | I13: Returning | J13: Port Harcourt | K13: Instagram
... A15: EC2014 | B15: 46100 | C15: Hoodie | D15: Fashion | E15: 4 | F15: 17500 | G15: 70000 | H15: Transfer | I15: Returning | J15: Port Harcourt | K15: Marketplace
A16: EC2015 | B16: 46157 | C16: Gel Pen Pack | D16: Stationery | E16: 4 | F16: 1800 | G16: 7200 | I16: New | J16: Abuja | K16: WhatsApp
A17: EC2016 | B17: 46110 | C17: Notebook | D17: Stationery | E17: 1 | F17: 2500 | G17: 2500 | H17: POS | I17: Returning | J17: Ibadan | K17: Marketplace
A18: EC2017 | B18: 46062 | C18: Sunglasses | D18: Fashion | E18: 4 | F18: 8000 | G18: 32000 | H18: POS | I18: Returning | J18: Abuja | K18: Website
A19: EC2018 | B19: 46072 | C19: Laptop Stand | D19: Accessories | E19: 4 | F19: 14500 | G19: 58000 | H19: Cash | I19: New | J19: Lagos | K19: Website
A20: EC2019 | B20: 46132 | C20: Notebook | D20: Stationery | E20: 1 | F20: 2500 | G20: 2500 | H20: Transfer | I20: New | J20: Lagos | K20: Website
A21: EC2020 | B21: 46139 | C21: Hoodie | D21: Fashion | E21: 3 | F21: 17500 | G21: 52500 | H21: POS | I21: New | J21: Lagos | K21: WhatsApp
A22: EC2021 | B22: 46142 | C22: Sneakers | D22: Fashion | E22: 4 | F22: 28000 | G22: 112000 | H22: Transfer | I22: New | J22: Port Harcourt | K22: Instagram
A23: EC2022 | B23: 46064 | C23: Planner | D23: Stationery | E23: 3 | F23: 5500 | G23: 16500 | H23: Cash | I23: New | J23: Ibadan | K23: WhatsApp
A24: EC2023 | B24: 46103 | C24: Gel Pen Pack | D24: Stationery | E24: 4 | F24: 1800 | G24: 7200 | H24: Transfer | I24: New | J24: Port Harcourt | K24: Website
A25: EC2024 | B25: 46167 | C25: Phone Charger | D25: Electronics | E25: 4 | F25: 7500 | G25: 30000 | H25: Card | I25: New | J25: Abuja | K25: WhatsApp
A26: EC2025 | B26: 46057 | C26: Phone Case | D26: Accessories | E26: 1 | F26: 4500 | G26: 4500 | H26: Cash | I26: Returning | J26: Abuja | K26: Marketplace
A27: EC2026 | B27: 46117 | C27: Water Bottle | D27: Home & Lifestyle | E27: 1 | F27: 6500 | G27: 6500 | H27: Cash | I27: New | J27: Ibadan | K27: Instagram
A28: EC2027 | B28: 46112 | C28: Desk Lamp | D28: Home & Lifestyle | E28: 3 | F28: 12000 | G28: 36000 | H28: Transfer | I28: New | J28: Benin City | K28: Marketplace
... A152: EC2055 | B152: 46082 | C152: Notebook | D152: Stationery | E152: 1 | F152: 2500 | G152: 2500 | H152: Transfer | I152: Returning | J152: Abuja | K152: Instagram

Sheet Cleaned Data
A1: Order ID | B1: Order Date | C1: Product | D1: Category | E1: Quantity | F1: Unit Price | G1: Sales Amount | H1: Payment Method | I1: Customer Type | J1: City | K1: Sales Channel | L1: Month
A2: EC2001 | B2: 46118 | C2: Phone Charger | D2: Electronics | E2: 3 | F2: 7500 | G2: 22500 | H2: Card | I2: New | J2: Benin City | K2: Marketplace | L2: =TEXT($B2,"mmmm") -> April
A3: EC2002 | B3: 46150 | C3: Hoodie | D3: Fashion | E3: 4 | F3: 17500 | G3: 70000 | H3: Cash | I3: New | J3: Lagos | K3: Website | L3: =TEXT($B3,"mmmm") -> May
A4: EC2003 | B4: 46158 | C4: Phone Charger | D4: Electronics | E4: 3 | F4: 7500 | G4: 22500 | H4: Card | I4: Returning | J4: Lagos | K4: Marketplace | L4: =TEXT($B4,"mmmm") -> May
A5: EC2004 | B5: 46080 | C5: Sneakers | D5: Fashion | E5: 3 | F5: 28000 | G5: 84000 | H5: Cash | I5: Returning | J5: Abuja | K5: WhatsApp | L5: =TEXT($B5,"mmmm") -> February
A6: EC2005 | B6: 46149 | C6: Hoodie | D6: Fashion | E6: 4 | F6: 17500 | G6: 70000 | H6: Card | I6: Returning | J6: Lagos | K6: WhatsApp | L6: =TEXT($B6,"mmmm") -> May
A7: EC2006 | B7: 46072 | C7: Backpack | D7: Accessories | E7: 4 | F7: 18000 | G7: 72000 | H7: POS | I7: New | J7: Abuja | K7: WhatsApp | L7: =TEXT($B7,"mmmm") -> February
A8: EC2007 | B8: 46065 | C8: Notebook | D8: Stationery | E8: 4 | F8: 2500 | G8: 10000 | H8: Cash | I8: Returning | J8: Lagos | K8: Marketplace | L8: =TEXT($B8,"mmmm") -> February
A9: EC2008 | B9: 46104 | C9: Gel Pen Pack | D9: Stationery | E9: 4 | F9: 1800 | G9: 7200 | H9: POS | I9: Returning | J9: Benin City | K9: Marketplace | L9: =TEXT($B9,"mmmm") -> March
A10: EC2009 | B10: 46127 | C10: Gel Pen Pack | D10: Stationery | E10: 1 | F10: 1800 | G10: 1800 | H10: Transfer | I10: New | J10: Lagos | K10: Website | L10: =TEXT($B10,"mmmm") -> April
A11: EC2010 | B11: 46114 | C11: T-Shirt | D11: Fashion | E11: 4 | F11: 9500 | G11: 38000 | H11: Transfer | I11: Returning | J11: Ibadan | K11: Website | L11: =TEXT($B11,"mmmm") -> April
A12: EC2011 | B12: 46140 | C12: Sneakers | D12: Fashion | E12: 4 | F12: 28000 | G12: 112000 | H12: Cash | I12: Returning | J12: Benin City | K12: Marketplace | L12: =TEXT($B12,"mmmm") -> April
A13: EC2012 | B13: 46124 | C13: Sneakers | D13: Fashion | E13: 3 | F13: 28000 | G13: 84000 | H13: Cash | I13: Returning | J13: Port Harcourt | K13: Instagram | L13: =TEXT($B13,"mmmm") -> April
... A151: EC2150 | B151: 46080 | C151: Planner | D151: Stationery | E151: 1 | F151: 5500 | G151: 5500 | H151: Transfer | I151: Returning | J151: Port Harcourt | K151: Instagram | L151: =TEXT($B151,"mmmm") -> February

Sheet Analysis
C1: Analysis
A3: Overall Analysis | D3: Customer Analysis
A4: Total Revenue | B4: =SUM('Cleaned Data'!G:G) -> 4546400 | D4: Revenue from New customers | E4: =SUMIFS('Cleaned Data'!G:G,'Cleaned Data'!I:I,"New") -> 1865100
A5: Total Quantity Sold | B5: =SUM('Cleaned Data'!E:E) -> 374 | D5: Revenue from Returning customers | E5: =SUMIFS('Cleaned Data'!G:G,'Cleaned Data'!I:I,"Returning") -> 2681300
A6: Average Sales Amount | B6: =AVERAGE('Cleaned Data'!G:G) -> 30309.333 | D6: Which customer type generated the most revenue | E6: =INDEX(Sheet3!F2:F3,MATCH(MAX(Sheet3!G2:G3),Sheet3!G2:G3,0)) -> Returning
A7: Highest Transaction | B7: =MAX('Cleaned Data'!G:G) -> 112000
A8: Lowest Transaction | B8: =MIN('Cleaned Data'!G:G) -> 1800
A9: Number Of Transactions | B9: =COUNTA('Cleaned Data'!A2:A151) -> 150
A13: Product Analysis | D13: Location Analysis
A14: Highest-revenue product | B14: =INDEX('Cleaned Data'!C:C,MATCH(MAX('Cleaned Data'!G:G),'Cleaned Data'!G:G,0)) -> Sneakers | D14: City with the highest revenue | E14: =INDEX(D17:D21,MATCH(MAX(E17:E21),E17:E21,0)) -> Abuja
A15: Lowest-revenue product | B15: =INDEX('Cleaned Data'!C:C,MATCH(MIN('Cleaned Data'!G:G),'Cleaned Data'!G:G,0)) -> Gel Pen Pack | D15: City with the lowest revenue | E15: =INDEX(D18:D22,MATCH(MIN(E18:E22),E18:E22,0)) -> Port Harcourt
A16: Highest-quantity product | B16: =INDEX($A$19:$A$33,MATCH(MAX(Sheet1!B2:B16),Sheet1!B2:B16,0)) -> Sneakers | D16: Revenue generated by each city:
A17: Lowest-quantity product | B17: =INDEX($A$19:$A$33,MATCH(MIN(Sheet1!B2:B16),Sheet1!B2:B16,0)) -> Wireless Earbuds | D17: Benin City | E17: =SUMIFS('Cleaned Data'!$G:$G,'Cleaned Data'!$J:$J,Sheet3!$H2) -> 867600
A18: Revenue generated by each product: | D18: Lagos | E18: =SUMIFS('Cleaned Data'!$G:$G,'Cleaned Data'!$J:$J,Sheet3!$H3) -> 980600
A19: Phone Charger | B19: =SUMIFS('Cleaned Data'!G:G,'Cleaned Data'!C:C,Analysis!$A19) -> 180000 | D19: Abuja | E19: =SUMIFS('Cleaned Data'!$G:$G,'Cleaned Data'!$J:$J,Sheet3!$H4) -> 1209000
A20: Hoodie | B20: =SUMIFS('Cleaned Data'!G:G,'Cleaned Data'!C:C,Analysis!$A20) -> 490000 | D20: Ibadan | E20: =SUMIFS('Cleaned Data'!$G:$G,'Cleaned Data'!$J:$J,Sheet3!$H5) -> 753300
A21: Sneakers | B21: =SUMIFS('Cleaned Data'!G:G,'Cleaned Data'!C:C,Analysis!$A21) -> 1232000 | D21: Port Harcourt | E21: =SUMIFS('Cleaned Data'!$G:$G,'Cleaned Data'!$J:$J,Sheet3!$H6) -> 735900
A22: Backpack | B22: =SUMIFS('Cleaned Data'!G:G,'Cleaned Data'!C:C,Analysis!$A22) -> 450000
A23: Notebook | B23: =SUMIFS('Cleaned Data'!G:G,'Cleaned Data'!C:C,Analysis!$A23) -> 52500
A24: Gel Pen Pack | B24: =SUMIFS('Cleaned Data'!G:G,'Cleaned Data'!C:C,Analysis!$A24) -> 68400
A25: T-Shirt | B25: =SUMIFS('Cleaned Data'!G:G,'Cleaned Data'!C:C,Analysis!$A25) -> 237500
A26: Sunglasses | B26: =SUMIFS('Cleaned Data'!G:G,'Cleaned Data'!C:C,Analysis!$A26) -> 224000 | D26: Payment Analysis
A27: Laptop Stand | B27: =SUMIFS('Cleaned Data'!G:G,'Cleaned Data'!C:C,Analysis!$A27) -> 348000 | D27: Most frequently used payment method | E27: =INDEX(D29:D32,MATCH(MAX(E29:E32),E29:E32,0)) -> Card
A28: Planner | B28: =SUMIFS('Cleaned Data'!G:G,'Cleaned Data'!C:C,Analysis!$A28) -> 143000 | D28: Numbers of transactions for each method:
A29: Phone Case | B29: =SUMIFS('Cleaned Data'!G:G,'Cleaned Data'!C:C,Analysis!$A29) -> 85500 | D29: Card | E29: =COUNTIF('Cleaned Data'!$H:$H,Analysis!$D29) -> 46
A30: Water Bottle | B30: =SUMIFS('Cleaned Data'!G:G,'Cleaned Data'!C:C,Analysis!$A30) -> 149500 | D30: Cash | E30: =COUNTIF('Cleaned Data'!$H:$H,Analysis!$D30) -> 30
A31: Desk Lamp | B31: =SUMIFS('Cleaned Data'!G:G,'Cleaned Data'!C:C,Analysis!$A31) -> 180000 | D31: POS | E31: =COUNTIF('Cleaned Data'!$H:$H,Analysis!$D31) -> 37
A32: Wireless Earbuds | B32: =SUMIFS('Cleaned Data'!G:G,'Cleaned Data'!C:C,Analysis!$A32) -> 222000 | D32: Transfer | E32: =COUNTIF('Cleaned Data'!$H:$H,Analysis!$D32) -> 37
A33: Power Bank | B33: =SUMIFS('Cleaned Data'!G:G,'Cleaned Data'!C:C,Analysis!$A33) -> 484000
A37: Category Analysis | D37: Sales Channel Analysis
A38: Highest-revenue category | B38: =INDEX('Cleaned Data'!D:D,MATCH(MAX('Cleaned Data'!G:G),'Cleaned Data'!G:G,0)) -> Fashion | D38: Number of transactions by sales channel | E38: =SUM(Sheet3!N2:N5) -> 150
A39: Lowest-revenue category | B39: =INDEX('Cleaned Data'!D:D,MATCH(MIN('Cleaned Data'!G:G),'Cleaned Data'!G:G,0)) -> Stationery | D39: Highest-revenue sales channel | E39: =INDEX(Sheet3!$M$2:$M$5,MATCH(MAX(Sheet3!$N$2:$N$5),Sheet3!$N$2:$N$5,0)) -> Marketplace
A40: Revenue generated by each category: | D40: Lowest-revenue sales channel | E40: =INDEX(Sheet3!$M$2:$M$5,MATCH(MIN(Sheet3!$N$2:$N$5),Sheet3!$N$2:$N$5,0)) -> Website
A41: Electronics | B41: =SUMIFS('Cleaned Data'!G:G,'Cleaned Data'!D:D,$A41) -> 886000 | D41: Revenue generated by each sales channel:
A42: Fashion | B42: =SUMIFS('Cleaned Data'!G:G,'Cleaned Data'!D:D,$A42) -> 2183500 | D42: Marketplace | E42: =SUMIFS('Cleaned Data'!$G:$G,'Cleaned Data'!K:K,$D42) -> 1318300
A43: Accessories | B43: =SUMIFS('Cleaned Data'!G:G,'Cleaned Data'!D:D,$A43) -> 883500 | D43: Website | E43: =SUMIFS('Cleaned Data'!$G:$G,'Cleaned Data'!K:K,$D43) -> 838500
A44: Stationery | B44: =SUMIFS('Cleaned Data'!G:G,'Cleaned Data'!D:D,$A44) -> 263900 | D44: WhatsApp | E44: =SUMIFS('Cleaned Data'!$G:$G,'Cleaned Data'!K:K,$D44) -> 1266800
A45: Home & Lifestyle | B45: =SUMIFS('Cleaned Data'!G:G,'Cleaned Data'!D:D,$A45) -> 329500 | D45: Instagram | E45: =SUMIFS('Cleaned Data'!$G:$G,'Cleaned Data'!K:K,$D45) -> 1122800

Sheet Sheet3
A1: Category | C1: Product | D1: sales | E1: quantity | H1: City | J1: Payment Method | M1: Sales Channel | R1: Row Labels | S1: Sum of Sales Amount
A2: Electronics | B2: =SUMIFS('Cleaned Data'!G:G,'Cleaned Data'!D:D,$A2) -> 886000 | C2: Phone Charger | D2: =SUMIFS('Cleaned Data'!G:G,'Cleaned Data'!C:C,Sheet3!$C$2) -> 180000 | E2: =SUMIFS('Cleaned Data'!E:E,'Cleaned Data'!C:C,Sheet3!$C2) -> 24 | F2: New | G2: =SUMIFS('Cleaned Data'!G:G,'Cleaned Data'!I:I,Sheet3!$F2) -> 1865100 | H2: Benin City | I2: =SUMIFS('Cleaned Data'!$G:$G,'Cleaned Data'!$J:$J,Sheet3!$H$2) -> 867600 | J2: Card | K2: =SUMIFS('Cleaned Data'!$G:$G,'Cleaned Data'!$H:$H,Sheet3!$J$2) -> 1387200 | L2: =COUNTIF('Cleaned Data'!H:H,Sheet3!$J2) -> 46 | M2: Marketplace | N2: =COUNTIF('Cleaned Data'!$K:$K,Sheet3!$M$2) -> 42 | O2: April | P2: =SUMIFS('Cleaned Data'!G2:G151,'Cleaned Data'!L2:L151,Sheet3!$O2) -> 1527400 | Q2: =SUMIFS('Cleaned Data'!G:G,Sheet3!O:O,Sheet3!$P2) -> 0 | R2: February | S2: 1153000
A3: Fashion | B3: =SUMIFS('Cleaned Data'!G:G,'Cleaned Data'!D:D,$A3) -> 2183500 | C3: Hoodie | D3: =SUMIFS('Cleaned Data'!G:G,'Cleaned Data'!C:C,Sheet3!$C3) -> 490000 | E3: =SUMIFS('Cleaned Data'!E:E,'Cleaned Data'!C:C,Sheet3!$C3) -> 28 | F3: Returning | G3: =SUMIFS('Cleaned Data'!G:G,'Cleaned Data'!I:I,Sheet3!$F3) -> 2681300 | H3: Lagos | I3: =SUMIFS('Cleaned Data'!G:G,'Cleaned Data'!J:J,Sheet3!$H3) -> 980600 | J3: Cash | K3: =SUMIFS('Cleaned Data'!$G:$G,'Cleaned Data'!$H:$H,Sheet3!$J3) -> 1158000 | L3: =COUNTIF('Cleaned Data'!H:H,Sheet3!$J3) -> 30 | M3: Website | N3: =COUNTIF('Cleaned Data'!K:K,Sheet3!$M3) -> 27 | O3: March | R3: March | S3: 1057300
A4: Accessories | B4: =SUMIFS('Cleaned Data'!G:G,'Cleaned Data'!D:D,$A4) -> 883500 | C4: Sneakers | D4: =SUMIFS('Cleaned Data'!G:G,'Cleaned Data'!C:C,Sheet3!$C4) -> 1232000 | E4: =SUMIFS('Cleaned Data'!E:E,'Cleaned Data'!C:C,Sheet3!$C4) -> 44 | G4: =INDEX(F2:F3,MATCH(MAX(G2:G3),G2:G3,0)) -> Returning | H4: Abuja | I4: =SUMIFS('Cleaned Data'!G:G,'Cleaned Data'!J:J,Sheet3!$H4) -> 1209000 | J4: POS | K4: =SUMIFS('Cleaned Data'!$G:$G,'Cleaned Data'!$H:$H,Sheet3!$J4) -> 1049300 | L4: =COUNTIF('Cleaned Data'!H:H,Sheet3!$J4) -> 37 | M4: WhatsApp | N4: =COUNTIF('Cleaned Data'!K:K,Sheet3!$M4) -> 41 | O4: May | R4: April | S4: 1527400
A5: Stationery | B5: =SUMIFS('Cleaned Data'!G:G,'Cleaned Data'!D:D,$A5) -> 263900 | C5: Backpack | D5: =SUMIFS('Cleaned Data'!G:G,'Cleaned Data'!C:C,Sheet3!$C5) -> 450000 | E5: =SUMIFS('Cleaned Data'!E:E,'Cleaned Data'!C:C,Sheet3!$C5) -> 25 | H5: Ibadan | I5: =SUMIFS('Cleaned Data'!G:G,'Cleaned Data'!J:J,Sheet3!$H5) -> 753300 | J5: Transfer | K5: =SUMIFS('Cleaned Data'!$G:$G,'Cleaned Data'!$H:$H,Sheet3!$J5) -> 951900 | L5: =COUNTIF('Cleaned Data'!H:H,Sheet3!$J5) -> 37 | M5: Instagram | N5: =COUNTIF('Cleaned Data'!K:K,Sheet3!$M5) -> 40 | O5: February | R5: May | S5: 808700
A6: Home & Lifestyle | B6: =SUMIFS('Cleaned Data'!G:G,'Cleaned Data'!D:D,$A6) -> 329500 | C6: Notebook | D6: =SUMIFS('Cleaned Data'!G:G,'Cleaned Data'!C:C,Sheet3!$C6) -> 52500 | E6: =SUMIFS('Cleaned Data'!E:E,'Cleaned Data'!C:C,Sheet3!$C6) -> 21 | H6: Port Harcourt | I6: =SUMIFS('Cleaned Data'!G:G,'Cleaned Data'!J:J,Sheet3!$H6) -> 735900 | R6: Grand Total | S6: 4546400
C7: Gel Pen Pack | D7: =SUMIFS('Cleaned Data'!G:G,'Cleaned Data'!C:C,Sheet3!$C7) -> 68400 | E7: =SUMIFS('Cleaned Data'!E:E,'Cleaned Data'!C:C,Sheet3!$C7) -> 38
C8: T-Shirt | D8: =SUMIFS('Cleaned Data'!G:G,'Cleaned Data'!C:C,Sheet3!$C8) -> 237500 | E8: =SUMIFS('Cleaned Data'!E:E,'Cleaned Data'!C:C,Sheet3!$C8) -> 25 | O8: Row Labels | P8: Sum of Sales Amount
C9: Sunglasses | D9: =SUMIFS('Cleaned Data'!G:G,'Cleaned Data'!C:C,Sheet3!$C9) -> 224000 | E9: =SUMIFS('Cleaned Data'!E:E,'Cleaned Data'!C:C,Sheet3!$C9) -> 28 | O9: Backpack | P9: 450000
C10: Laptop Stand | D10: =SUMIFS('Cleaned Data'!G:G,'Cleaned Data'!C:C,Sheet3!$C10) -> 348000 | E10: =SUMIFS('Cleaned Data'!E:E,'Cleaned Data'!C:C,Sheet3!$C10) -> 24 | O10: Desk Lamp | P10: 180000
C11: Planner | D11: =SUMIFS('Cleaned Data'!G:G,'Cleaned Data'!C:C,Sheet3!$C11) -> 143000 | E11: =SUMIFS('Cleaned Data'!E:E,'Cleaned Data'!C:C,Sheet3!$C11) -> 26 | O11: Gel Pen Pack | P11: 68400
C12: Phone Case | D12: =SUMIFS('Cleaned Data'!G:G,'Cleaned Data'!C:C,Sheet3!$C12) -> 85500 | E12: =SUMIFS('Cleaned Data'!E:E,'Cleaned Data'!C:C,Sheet3!$C12) -> 19 | O12: Hoodie | P12: 490000
C13: Water Bottle | D13: =SUMIFS('Cleaned Data'!G:G,'Cleaned Data'!C:C,Sheet3!$C13) -> 149500 | E13: =SUMIFS('Cleaned Data'!E:E,'Cleaned Data'!C:C,Sheet3!$C13) -> 23 | O13: Laptop Stand | P13: 348000
C14: Desk Lamp | D14: =SUMIFS('Cleaned Data'!G:G,'Cleaned Data'!C:C,Sheet3!$C14) -> 180000 | E14: =SUMIFS('Cleaned Data'!E:E,'Cleaned Data'!C:C,Sheet3!$C14) -> 15 | O14: Notebook | P14: 52500
C15: Wireless Earbuds | D15: =SUMIFS('Cleaned Data'!G:G,'Cleaned Data'!C:C,Sheet3!$C15) -> 222000 | E15: =SUMIFS('Cleaned Data'!E:E,'Cleaned Data'!C:C,Sheet3!$C15) -> 12 | O15: Phone Case | P15: 85500
C16: Power Bank | D16: =SUMIFS('Cleaned Data'!G:G,'Cleaned Data'!C:C,Sheet3!$C16) -> 484000 | E16: =SUMIFS('Cleaned Data'!E:E,'Cleaned Data'!C:C,Sheet3!$C16) -> 22 | O16: Phone Charger | P16: 180000
O17: Planner | P17: 143000
O18: Power Bank | P18: 484000
O19: Sneakers | P19: 1232000
O20: Sunglasses | P20: 224000
O21: T-Shirt | P21: 237500
O22: Water Bottle | P22: 149500
O23: Wireless Earbuds | P23: 222000
O24: Grand Total | P24: 4546400

Sheet Monthly Analysis
A1: Monthly Analysis
A3: Revenue for each month:
A4: February | B4: =SUMIFS('Cleaned Data'!$G:$G,'Cleaned Data'!$L:$L,'Monthly Analysis'!$A4) -> 1153000
A5: March | B5: =SUMIFS('Cleaned Data'!$G:$G,'Cleaned Data'!$L:$L,'Monthly Analysis'!$A5) -> 1057300
A6: May | B6: =SUMIFS('Cleaned Data'!$G:$G,'Cleaned Data'!$L:$L,'Monthly Analysis'!$A6) -> 808700
A7: April | B7: =SUMIFS('Cleaned Data'!$G:$G,'Cleaned Data'!$L:$L,'Monthly Analysis'!$A7) -> 1527400
A10: Quantity sold each month:
A11: February | B11: =SUMIFS('Cleaned Data'!E:E,'Cleaned Data'!L:L,'Monthly Analysis'!$A11) -> 99
A12: March | B12: =SUMIFS('Cleaned Data'!E:E,'Cleaned Data'!L:L,'Monthly Analysis'!$A12) -> 94
A13: May | B13: =SUMIFS('Cleaned Data'!E:E,'Cleaned Data'!L:L,'Monthly Analysis'!$A13) -> 67
A14: April | B14: =SUMIFS('Cleaned Data'!E:E,'Cleaned Data'!L:L,'Monthly Analysis'!$A14) -> 114
A17: Number of transactions each month:
A18: February | B18: =COUNTIFS('Cleaned Data'!L:L,'Monthly Analysis'!A18) -> 38
A19: March | B19: =COUNTIFS('Cleaned Data'!L:L,'Monthly Analysis'!A19) -> 37
A20: May | B20: =COUNTIFS('Cleaned Data'!L:L,'Monthly Analysis'!A20) -> 30
A21: April | B21: =COUNTIFS('Cleaned Data'!L:L,'Monthly Analysis'!A21) -> 45
A24: Highest-revenue month: | B24: =INDEX(A4:A7,MATCH(MAX(B4:B7),B4:B7,0)) -> April
A25: Lowest-revenue month: | B25: =INDEX(A4:A7,MATCH(MIN(B4:B7),B4:B7,0)) -> May

Sheet Pivot Analysis
D1: Pivot Analysis
A4: Products | B4: Sum of Sales Amount | E4: Payment Method | F4: Sum of Sales Amount
A5: Backpack | B5: 450000 | E5: Card | F5: 1387200
A6: Desk Lamp | B6: 180000 | E6: Cash | F6: 1158000
A7: Gel Pen Pack | B7: 68400 | E7: POS | F7: 1049300
A8: Hoodie | B8: 490000 | E8: Transfer | F8: 951900
A9: Laptop Stand | B9: 348000 | E9: Grand Total | F9: 4546400
A10: Notebook | B10: 52500
A11: Phone Case | B11: 85500
A12: Phone Charger | B12: 180000
A13: Planner | B13: 143000 | E13: Months | F13: Sum of Sales Amount
A14: Power Bank | B14: 484000 | E14: February | F14: 1153000
A15: Sneakers | B15: 1232000 | E15: March | F15: 1057300
A16: Sunglasses | B16: 224000 | E16: April | F16: 1527400
A17: T-Shirt | B17: 237500 | E17: May | F17: 808700
A18: Water Bottle | B18: 149500 | E18: Grand Total | F18: 4546400
A19: Wireless Earbuds | B19: 222000
A20: Grand Total | B20: 4546400
A24: Categoreis | B24: Sum of Sales Amount | E24: Sales Channel | F24: Sum of Sales Amount
A25: Accessories | B25: 883500 | E25: Instagram | F25: 1122800
A26: Electronics | B26: 886000 | E26: Marketplace | F26: 1318300
A27: Fashion | B27: 2183500 | E27: Website | F27: 838500
A28: Home & Lifestyle | B28: 329500 | E28: WhatsApp | F28: 1266800
A29: Stationery | B29: 263900 | E29: Grand Total | F29: 4546400
A30: Grand Total | B30: 4546400
A34: City | B34: Sum of Sales Amount | E34: Customer Type | F34: Sum of Sales Amount
A35: Abuja | B35: 1209000 | E35: New | F35: 1865100
A36: Benin City | B36: 867600 | E36: Returning | F36: 2681300
A37: Ibadan | B37: 753300 | E37: Grand Total | F37: 4546400
A38: Lagos | B38: 980600
A39: Port Harcourt | B39: 735900
A40: Grand Total | B40: 4546400

Sheet Dashboard
F1: Dashboard for EcoCart Data

Sheet Insights&Recommendations
A1: Insights
A2: Fashion dominates (₦2,183,500 — nearly half of total revenue), driven largely by Sneakers (₦1,232,000, also highest quantity sold)
A3: Stationery is the weakest category (₦263,900); Gel Pen Pack is the lowest-revenue product
A4: Electronics and Accessories perform similarly (₦885K each) — a stable secondary tier
A5: Returning customers generated ₦2,681,300 in revenue than new ones with ₦1,865,100.
A6: Abuja leads (₦1,209,000), Port Harcourt lags (₦735,900) — a ₦473K gap between top and bottom city
A7: Marketplace is the top sales channel (₦1,318,300, 42 transactions), Website is weakest (₦838,500, only 27 transactions) despite similar transaction volume to WhatsApp/Instagram
A8: Card is the most-used payment method, followed closely by Cash — POS and Transfer trail
A9: April was the peak month (₦1,527,400, 114 units, 45 transactions) — nearly double May’s ₦808,700. Worth investigating what drove the April spike (promotion? seasonal demand?) and why May dropped off
A12: Recommendations
A13: Double down on Fashion/Sneakers — it’s the clear revenue driver; consider expanding SKUs or bundling with Accessories to lift average order value.
A14: Re-evaluate Stationery — either reposition (bundle with other categories) or scale back inventory investment given weak returns.
... A18: Explore underperforming cities (Port Harcourt, Ibadan) — targeted local promotions or logistics improvements could close the gap with Abuja/Lagos.

Sheet Executive Summary
A1: Executive Summary
A2: EcoCart generated ₦4,546,400 in revenue from 150 transactions between February and May. Fashion — led by Sneakers — is the standout category, while Stationery underperforms. Returning customers are more valuable than new ones, and Marketplace is the strongest sales channel, with Website notably lagging. Abuja is the top-performing city; Port Harcourt the weakest. Revenue peaked sharply in April before falling in May, pointing to a seasonal or promotional effect worth replicating. Overall, the business shows healthy customer retention and a clear category winner, but has room to improve underperforming channels, regions, and product lines.

Sheet Sheet1
A1: =SUMIFS('Cleaned Data'!E:E,Analysis!$A$19:$A$33,$A19) -> #VALUE!
A2: Phone Charger | B2: =SUMIFS('Cleaned Data'!E:E,'Cleaned Data'!C:C,$A2) -> 24
A3: Hoodie | B3: =SUMIFS('Cleaned Data'!E:E,'Cleaned Data'!C:C,$A3) -> 28
A4: Sneakers | B4: =SUMIFS('Cleaned Data'!E:E,'Cleaned Data'!C:C,$A4) -> 44
A5: Backpack | B5: =SUMIFS('Cleaned Data'!E:E,'Cleaned Data'!C:C,$A5) -> 25
A6: Notebook | B6: =SUMIFS('Cleaned Data'!E:E,'Cleaned Data'!C:C,$A6) -> 21
A7: Gel Pen Pack | B7: =SUMIFS('Cleaned Data'!E:E,'Cleaned Data'!C:C,$A7) -> 38
A8: T-Shirt | B8: =SUMIFS('Cleaned Data'!E:E,'Cleaned Data'!C:C,$A8) -> 25
A9: Sunglasses | B9: =SUMIFS('Cleaned Data'!E:E,'Cleaned Data'!C:C,$A9) -> 28
A10: Laptop Stand | B10: =SUMIFS('Cleaned Data'!E:E,'Cleaned Data'!C:C,$A10) -> 24
A11: Planner | B11: =SUMIFS('Cleaned Data'!E:E,'Cleaned Data'!C:C,$A11) -> 26
A12: Phone Case | B12: =SUMIFS('Cleaned Data'!E:E,'Cleaned Data'!C:C,$A12) -> 19
A13: Water Bottle | B13: =SUMIFS('Cleaned Data'!E:E,'Cleaned Data'!C:C,$A13) -> 23
... A16: Power Bank | B16: =SUMIFS('Cleaned Data'!E:E,'Cleaned Data'!C:C,$A16) -> 22
